pyshotter/__init__.py
pyshotter/__main__.py
pyshotter/base.py
pyshotter/darwin.py
pyshotter/exception.py
pyshotter/factory.py
pyshotter/features.py
pyshotter/linux.py
pyshotter/models.py
pyshotter/py.typed
pyshotter/screenshot.py
pyshotter/tools.py
pyshotter/windows.py
pyshotter-1.0.0.dist-info/METADATA
pyshotter-1.0.0.dist-info/WHEEL
pyshotter-1.0.0.dist-info/entry_points.txt
pyshotter-1.0.0.dist-info/licenses/LICENSE.txt
pyshotter-1.0.0.dist-info/RECORD
