Metadata-Version: 2.4
Name: pyshotter
Version: 1.0.0
Summary: PyShotter: Smart, annotated, and shareable screenshots for Python.
Project-URL: Homepage, https://github.com/utachicodes/pyshotter
Project-URL: Documentation, https://github.com/utachicodes/pyshotter#readme
Project-URL: Changelog, https://github.com/utachicodes/pyshotter/blob/main/CHANGELOG.md
Project-URL: Source, https://github.com/utachicodes/pyshotter
Project-URL: Tracker, https://github.com/utachicodes/pyshotter/issues
Author-email: Abdoullah Ndao <abdoullahaljersi@gmail.com>
Maintainer-email: Abdoullah Ndao <abdoullahaljersi@gmail.com>
License: MIT License
License-File: LICENSE.txt
Keywords: annotation,change detection,cross-platform,history,hotkeys,ocr,panorama,python,redaction,screen capture,screenshot,sharing,smart detection,text extraction
Classifier: Development Status :: 5 - Production/Stable
Classifier: Environment :: MacOS X
Classifier: Intended Audience :: Developers
Classifier: Intended Audience :: End Users/Desktop
Classifier: License :: OSI Approved :: MIT License
Classifier: Operating System :: MacOS
Classifier: Operating System :: Microsoft :: Windows
Classifier: Operating System :: Unix
Classifier: Programming Language :: Python :: 3
Classifier: Programming Language :: Python :: 3.9
Classifier: Programming Language :: Python :: 3.10
Classifier: Programming Language :: Python :: 3.11
Classifier: Programming Language :: Python :: 3.12
Classifier: Topic :: Multimedia :: Graphics :: Capture :: Screen Capture
Classifier: Topic :: Scientific/Engineering :: Image Processing
Classifier: Topic :: Software Development :: Libraries
Classifier: Topic :: Text Processing :: Linguistic
Requires-Python: >=3.9
Provides-Extra: annotation
Requires-Dist: opencv-python>=4.8.0; extra == 'annotation'
Requires-Dist: pillow>=9.0.0; extra == 'annotation'
Provides-Extra: cloud
Requires-Dist: dropbox>=11.36.0; extra == 'cloud'
Requires-Dist: requests>=2.31.0; extra == 'cloud'
Provides-Extra: ocr
Requires-Dist: opencv-python>=4.8.0; extra == 'ocr'
Requires-Dist: pytesseract>=0.3.10; extra == 'ocr'
Provides-Extra: sharing
Requires-Dist: pyperclip>=1.8.0; extra == 'sharing'
Requires-Dist: requests>=2.31.0; extra == 'sharing'
